Metadata-Version: 2.1
Name: pentestgpt
Version: 0.8.0
Summary: PentestGPT, a GPT-empowered penetration testing tool
Home-page: https://github.com/GreyDGL/PentestGPT
Author: Gelei Deng
Author-email: gelei.deng@ntu.edu.sg
Maintainer: Gelei Deng
Maintainer-email: gelei.deng@ntu.edu.sg
License: MIT License
Project-URL: Code, https://github.com/GreyDGL/PentestGPT
Project-URL: Issue tracker, https://github.com/GreyDGL/PentestGPT/issues
License-File: LICENSE.md
